{
    "": "",
    "APIMethodCounter": "Compteur de méthodes API",
    "Abbreviation": "Abréviation",
    "AclActionCode": "Code d&#39;action Acl",
    "AclActionID": "Action Acl #",
    "AclAuthorized": "Acl autorisé",
    "AclPermission": "Autorisation Acl",
    "AclPublic": "Acl Public",
    "AclResourceID": "Ressource Acl #",
    "Action": "Action",
    "ActionID": "Action #",
    "ActivatedByDefault": "Activé par défaut",
    "ActivationModel": "Modèle d&#39;activation",
    "Badge": "Badge",
    "Body": "Corps",
    "ChildFeatureCode": "Code de fonctionnalité enfant",
    "ChildModuleCode": "Code du module enfant",
    "ChildOrdered": "Enfant commandé",
    "Class": "Classe",
    "Classification": "Classification",
    "Code": "Code",
    "CommonNotificationCode": "Code de notification commun",
    "CustomActivation": "Activation personnalisée",
    "Description": "Description",
    "Disabled": "Désactivé",
    "EmailModel": "Modèle de courrier électronique",
    "ExtraModuleCode": "Code du module supplémentaire",
    "Feature": "Fonctionnalité",
    "FeatureCode": "Code de fonctionnalité",
    "Finish": "Finition",
    "FlagID": "Drapeau #",
    "FormCode": "Code du formulaire",
    "FormPk": "Formulaire Pk",
    "FormUpdateID": "Mise à jour du formulaire #",
    "FormatColonColongetDatePlaceholder": "Format::getDatePlaceholder",
    "Format__getDatePlaceholder": "Format::getDatePlaceholder",
    "FormatgetDatePlaceholder": "Format::getDatePlaceholder",
    "Group1": "Groupe 1",
    "Group2": "Groupe 2",
    "Group3": "Groupe 3",
    "Group4": "Groupe 4",
    "Group5": "Groupe 5",
    "Group6": "Groupe 6",
    "Group7": "Groupe 7",
    "Group8": "Groupe 8",
    "Group9": "Groupe 9",
    "Icon": "Icône",
    "Important": "Important",
    "Inactive": "Inactif",
    "InsertedDatetime": "Date et heure insérées",
    "InsertedUserID": "Utilisateur inséré #",
    "Message": "Message",
    "MethodCode": "Code de méthode",
    "MethodName": "Nom de la méthode",
    "Module": "Module",
    "ModuleCode": "Code du module",
    "Multiple": "Multiple",
    "Name": "Nom",
    "NameGenerator": "Générateur de noms",
    "OperationDetails": "Détails de l&#39;opération",
    "OperationName": "Nom de l&#39;opération",
    "OptionsGenerator": "Générateur d&#39;options",
    "Order": "Commande",
    "ParentFeatureCode": "Code de fonctionnalité parent",
    "ParentFlagID": "Drapeau parent #",
    "ParentID": "Parent #",
    "ParentModuleCode": "Code du module parent",
    "ParentSubresourceID": "Sous-ressource parente #",
    "Percent": "Pour cent",
    "ProgressID": "Progrès #",
    "Prohibitive": "Prohibitif",
    "RequiresTenants": "Nécessite des locataires",
    "ResetModel": "Réinitialiser le modèle",
    "Resource": "Ressource",
    "ResourceID": "Ressource #",
    "RoleCodescommaSeparated": "Codes de rôle (séparés par des virgules)",
    "Rolecodescommaseparated": "Codes de rôle (séparés par des virgules)",
    "RootNode": "Nœud racine",
    "SMFormFields": "Champs de formulaire S/M",
    "SMFormUpdates": "Mises à jour du formulaire S/M",
    "SMForms": "Formulaires S/M",
    "SMModuleDependencies": "Dépendances des modules S/M",
    "SMModuleFeatures": "Caractéristiques du module S/M",
    "SMModules": "Modules S/M",
    "SMNotifications": "Notifications S/M",
    "SMResourceAPIMethods": "Méthodes de l&#39;API des ressources S/M",
    "SMResourceActions": "Actions sur les ressources S/M",
    "SMResourceFeatures": "Caractéristiques des ressources S/M",
    "SMResourceMap": "Carte des ressources S/M",
    "SMResourceMethods": "Méthodes de ressources S/M",
    "SMResourceTenants": "Locataires de ressources S/M",
    "SMResources": "Ressources S/M",
    "SMSubresourceFeatures": "Fonctionnalités des sous-ressources S/M",
    "SMSubresources": "Sous-ressources S/M",
    "SMSystemFlags": "Drapeaux du système S/M",
    "SMTaskProgresses": "Progression des tâches S/M",
    "Separator": "Séparateur",
    "Sequence": "Séquence",
    "SubformPk": "Sous-formulaire Pk",
    "Subject": "Sujet",
    "SubresourceID": "Sous-ressource #",
    "TasksCompleted": "Tâches accomplies",
    "TasksTotal": "Total des tâches",
    "TemplateName": "Nom du modèle",
    "TenantCode": "Code du locataire",
    "TenantID": "Locataire #",
    "Timestamp": "Horodatage",
    "Transactions": "Transactions",
    "Type": "Taper",
    "URL": "URL",
    "UpdatedDatetime": "Date et heure mises à jour",
    "UpdatedUserID": "Numéro d&#39;utilisateur mis à jour",
    "User": "Utilisateur",
    "VersionCode": "Code de version",
    "YesNo": "Oui / Non"
}