{
    "Attribute": "Atributo",
    "AttributeID": "Atributo #",
    "Code": "Código",
    "Domain": "Dominio",
    "EnvironmentMethod": "Método del entorno",
    "FlagABAC": "Bandera ABAC",
    "FlagAssignment": "Asignación de bandera",
    "FlagAttribute": "Atributo de bandera",
    "FlagLink": "Enlace de bandera",
    "FlagOtherTable": "Bandera Otra Tabla",
    "Inactive": "Inactivo",
    "IsNumericKey": "Es clave numérica",
    "LinkModelID": "Modelo de enlace n.°",
    "Model": "Modelo",
    "ModelID": "Modelo #",
    "Module": "Módulo",
    "ModuleCode": "Código del módulo",
    "Name": "Nombre",
    "ParentAttributeID": "Atributo principal n.°",
    "SMABACAssignments": "Asignaciones de S/M ABAC",
    "SMABACAttributes": "Atributos de S/M ABAC",
    "Sequence": "Secuencia",
    "Tenant": "Arrendatario",
    "Type": "Tipo",
    "YesNo": "Sí / No"
}