{
    "": "",
    "Code": "Código",
    "Command": "Dominio",
    "Description": "Descripción",
    "FinishTimestamp": "Marca de tiempo de finalización",
    "FormatColonColongetDatePlaceholder": "Formato::obtenerFechaMarcador de posición",
    "Format__getDatePlaceholder": "Formato::obtenerFechaMarcador de posición",
    "FormatgetDatePlaceholder": "Formato::obtenerFechaMarcador de posición",
    "Inactive": "Inactivo",
    "Model": "Modelo",
    "Module": "Módulo",
    "ModuleCode": "Código del módulo",
    "Name": "Nombre",
    "OptimisticLock": "Bloqueo optimista",
    "Percent": "Porcentaje (%)",
    "PercentComplate": "Porcentaje completado",
    "PercentPercent": "Porcentaje (%)",
    "RunID": "Correr #",
    "SMShellCommandRuns": "Ejecución de comandos de Shell S/M",
    "SMShellCommands": "Comandos de Shell S/M",
    "Sequence": "Secuencia",
    "ShellOutput": "Salida de Shell",
    "StartTimestamp": "Marca de tiempo de inicio",
    "Status": "Estado",
    "TenantID": "Arrendatario #",
    "Type": "Tipo",
    "User": "Usuario",
    "UserID": "Usuario #",
    "YesNo": "Sí / No"
}